<annotation>
	<folder>XML</folder>
	<filename>20638.jpg</filename>
	<path>F:\2_MyWork\1-Data-Vehicle\data_vehicle_21_01_2022\data_vehicle_2701\images\train\20638.jpg</path>
	<source>
		<database>Unknown</database>
	</source>
	<size>
		<width>393</width>
		<height>225</height>
		<depth>3</depth>
	</size>
	<segmented>0</segmented>
	<object>
		<name>vehicle plate</name>
		<pose>Unspecified</pose>
		<truncated>0</truncated>
		<difficult>0</difficult>
		<bndbox>
			<xmin>211</xmin>
			<ymin>120</ymin>
			<xmax>279</xmax>
			<ymax>140</ymax>
		</bndbox>
	</object>
</annotation>
