<annotation>
	<folder>XML</folder>
	<filename>21596.jpg</filename>
	<path>F:\2_MyWork\1-Data-Vehicle\data_vehicle_21_01_2022\data_vehicle_2701\images\train\21596.jpg</path>
	<source>
		<database>Unknown</database>
	</source>
	<size>
		<width>504</width>
		<height>480</height>
		<depth>3</depth>
	</size>
	<segmented>0</segmented>
	<object>
		<name>vehicle plate</name>
		<pose>Unspecified</pose>
		<truncated>0</truncated>
		<difficult>0</difficult>
		<bndbox>
			<xmin>307</xmin>
			<ymin>351</ymin>
			<xmax>388</xmax>
			<ymax>375</ymax>
		</bndbox>
	</object>
</annotation>
