<annotation>
  <folder>VOC2007</folder>
  <filename>video43.jpg</filename>
  <source>
    <database>Coco database</database>
  </source>
  <size>
    <width>1920</width>
    <height>1080</height>
    <depth>3</depth>
  </size>
  <segmented>0</segmented>
  <object>
    <name>vehicle-plate</name>
    <pose>Unspecified</pose>
    <truncated>0</truncated>
    <difficult>0</difficult>
    <bndbox>
      <xmin>3</xmin>
      <ymin>610</ymin>
      <xmax>128</xmax>
      <ymax>676</ymax>
    </bndbox>
  </object>
  <object>
    <name>vehicle-plate</name>
    <pose>Unspecified</pose>
    <truncated>0</truncated>
    <difficult>0</difficult>
    <bndbox>
      <xmin>1469</xmin>
      <ymin>399</ymin>
      <xmax>1554</xmax>
      <ymax>425</ymax>
    </bndbox>
  </object>
</annotation>
